brelpy/__init__.py
brelpy/device.py
brelpy/exceptions.py
brelpy/hub.py
brelpy/socket.py
brelpy/types.py
brelpy-0.0.3.dist-info/LICENSE
brelpy-0.0.3.dist-info/METADATA
brelpy-0.0.3.dist-info/WHEEL
brelpy-0.0.3.dist-info/top_level.txt
brelpy-0.0.3.dist-info/RECORD
